{
  "CA_OwnerID": "PL_PFSA",
  "EntityCode": "PSD_PI!PL_PFSA!6762165116!6180",
  "EntityType": "PSD_AG",
  "ENT_NAT_REF_COD": "6180",
  "ENT_NAM": "Piotr Siwulski Firma Handlowa \" Siwulski 4 \", Firma Handlowa \" Siwulski 5 \"",
  "ENT_ADD": "W3adys3awa Stanis3awa Reymonta 5361/5297, Maniowy, 34-436, PL",
  "ENT_TOW_CIT_RES": "Maniowy",
  "ENT_POS_COD": "34-436",
  "ENT_COU_RES": "PL",
  "ENT_TYP_PAR_ENT": "PSD_PI",
  "ENT_COD_PAR_ENT": "PL_PFSA!6762165116",
  "DER_CHI_ENT_AUT": "Active"
}
e"
}
